{
  "$schema": "file:///content/ModPacks/schemas/ServerMetaSchema.schema.json",
  "meta": {
    "version": "v2.2.1",
    "name": "LegacyCraft3 (Minecraft 1.12.2)",
    "description": "LegacyCraft3 Running Minecraft 1.12.2 (Forge v14.23.5.2860)",
    "icon": "How to set the server icon: https://github.com/dscalzi/Nebula#setting-the-server-icon",
    "address": "localhost:25565",
    "discord": {
      "shortId": "<FILL IN OR REMOVE DISCORD OBJECT>",
      "largeImageText": "<FILL IN OR REMOVE DISCORD OBJECT>",
      "largeImageKey": "<FILL IN OR REMOVE DISCORD OBJECT>"
    },
    "mainServer": false,
    "autoconnect": false
  },
  "forge": {
    "version": "14.23.5.2860"
  },
  "untrackedFiles": []
}